MANIFEST.in
README.md
pyproject.toml
setup.py
omuse_iemic.egg-info/PKG-INFO
omuse_iemic.egg-info/SOURCES.txt
omuse_iemic.egg-info/dependency_links.txt
omuse_iemic.egg-info/requires.txt
omuse_iemic.egg-info/top_level.txt
src/omuse/community/iemic/Makefile
src/omuse/community/iemic/__init__.py
src/omuse/community/iemic/implicit_utils.py
src/omuse/community/iemic/interface.cc
src/omuse/community/iemic/interface.hpp
src/omuse/community/iemic/interface.py
src/omuse/community/iemic/ocean_preconditioner_params.xml
src/omuse/community/iemic/paramset.cc
src/omuse/community/iemic/paramset.hpp
src/omuse/community/iemic/remotestatevector.py
src/omuse/community/iemic/setup.cfg
src/omuse/community/iemic/test_iemic.py
src/omuse/community/iemic/test_state.py
src/omuse/community/iemic/version.py
src/omuse/community/iemic/mkmask/mask_natl8
src/omuse/community/iemic/src/i-emic/.gitignore
src/omuse/community/iemic/src/i-emic/CMakeLists.txt
src/omuse/community/iemic/src/i-emic/LICENSE
src/omuse/community/iemic/src/i-emic/README.md
src/omuse/community/iemic/src/i-emic/cmake/CMakeLists.txt
src/omuse/community/iemic/src/i-emic/mrilu/CMakeLists.txt
src/omuse/community/iemic/src/i-emic/mrilu/Makefile
src/omuse/community/iemic/src/i-emic/mrilu/README
src/omuse/community/iemic/src/i-emic/mrilu/convprogs/Makefile
src/omuse/community/iemic/src/i-emic/mrilu/convprogs/amt2bmt.F90
src/omuse/community/iemic/src/i-emic/mrilu/convprogs/avc2bvc.F90
src/omuse/community/iemic/src/i-emic/mrilu/convprogs/avczn2avc.F90
src/omuse/community/iemic/src/i-emic/mrilu/convprogs/bmt2amt.F90
src/omuse/community/iemic/src/i-emic/mrilu/convprogs/bvc2avc.F90
src/omuse/community/iemic/src/i-emic/mrilu/convprogs/hbf2amt.F90
src/omuse/community/iemic/src/i-emic/mrilu/convprogs/stc2acsr.F90
src/omuse/community/iemic/src/i-emic/mrilu/convprogs/stc2bcsr.F90
src/omuse/community/iemic/src/i-emic/mrilu/convprogs/vsm2bmt.F90
src/omuse/community/iemic/src/i-emic/mrilu/convprogs/vsmb2bmt.F90
src/omuse/community/iemic/src/i-emic/mrilu/getdoc/Makefile
src/omuse/community/iemic/src/i-emic/mrilu/getdoc/README
src/omuse/community/iemic/src/i-emic/mrilu/getdoc/gendefs.c
